AUTHORS
CHANGES.txt
INSTALL
LICENSE
MANIFEST.in
README.rst
REQUIRED
setup.cfg
setup.py
setup_utils.py
sshpipe/__init__.py
sshpipe.egg-info/PKG-INFO
sshpipe.egg-info/SOURCES.txt
sshpipe.egg-info/dependency_links.txt
sshpipe.egg-info/requires.txt
sshpipe.egg-info/top_level.txt
sshpipe/bin/__init__.py
sshpipe/bin/sshpipe_socket_handler.py
sshpipe/lib/__init__.py
sshpipe/lib/pipe_listener.py
sshpipe/lib/ssh_remote_port.py
sshpipe/lib/ssh_tunnel.py
sshpipe/lib/sshconfig.py
sshpipe/lib/sshpipe.py
sshpipe/lib/sshpipe_callable_handler.py
sshpipe/lib/sshpipe_handler.py
sshpipe/lib/subprocess/__init__.py
sshpipe/lib/subprocess/sshsubprocessclient.py
sshpipe/lib/subprocess/sshsubprocessrun.py