Metadata-Version: 1.1
Name: sshpipe
Version: 0.5.2
Summary: sshpipe provide tools to manage ssh channel to remote hosts.
Home-page: https://github.com/Acrisel/sshpipe
Author: Acrisel Team
Author-email: support@acrisel.com
License: MIT
Keywords: library logger multiprocessing
Platform: UNKNOWN
Classifier: Development Status :: 4 - Beta
Classifier: Environment :: Other Environment
Classifier: Intended Audience :: Developers
Classifier: License :: OSI Approved :: MIT License
Classifier: Operating System :: OS Independent
Classifier: Programming Language :: Python
Classifier: Programming Language :: Python :: 3
Classifier: Topic :: System :: Distributed Computing
Classifier: Topic :: Software Development :: Libraries :: Python Modules
